[
    {
        "id": "news_6a41ded41563d_550e4c97",
        "industry": "科技",
        "source_name": "腾讯CDC",
        "source_url": "https:\/\/cdc.tencent.com\/feed\/",
        "title": "这类公益关乎你的精神需求",
        "url": "https:\/\/cdc.tencent.com\/2021\/12\/27\/%e8%bf%99%e7%b1%bb%e5%85%ac%e7%9b%8a%e5%85%b3%e4%b9%8e%e4%bd%a0%e7%9a%84%e7%b2%be%e7%a5%9e%e9%9c%80%e6%b1%82\/",
        "description": "​国内首个关注文化艺术公益领域的专业报告《2021中国文化艺术公益白皮书》（简称“白皮书”）正式发布，白皮书通 [&#8230;]",
        "image": "https:\/\/cdc-wp-blog-1258344706.cos.ap-guangzhou.myqcloud.com\/production\/wp-content\/uploads\/2021\/12\/官网封面.png",
        "publish_time": "2021-12-27 09:21:29",
        "crawl_time": "2026-06-29 02:56:20",
        "status": "active"
    }
]