[
    {
        "id": "news_6a41dedbdf9a6_0eeaec8d",
        "industry": "科技",
        "source_name": "张鑫旭博客",
        "source_url": "https:\/\/www.zhangxinxu.com\/wordpress\/feed\/",
        "title": "CSS contrast-color()函数简介",
        "url": "https:\/\/www.zhangxinxu.com\/wordpress\/2026\/06\/css-contrast-color\/",
        "description": "CSS终于出了个可以自动匹配色值对比度的函数，这在无障碍访问领域特别受用，前景背景色从此可以自动适配了。",
        "image": "\/\/image.zhangxinxu.com\/image\/blog\/201811\/auto-color-button.gif",
        "publish_time": "2026-06-01 14:54:42",
        "crawl_time": "2026-06-29 02:56:27",
        "status": "active"
    }
]